README.md
entsopy/__init__.py
entsopy/classes/__init__.py
entsopy/classes/article.py
entsopy/classes/httpsclient.py
entsopy/classes/request.py
entsopy/classes/response.py
entsopy/components/__init__.py
entsopy/components/areas.py
entsopy/components/article.py
entsopy/components/auction.py
entsopy/components/dates.py
entsopy/components/direction.py
entsopy/components/docstatus.py
entsopy/components/domain.py
entsopy/components/downloaddirectory.py
entsopy/components/home.py
entsopy/components/logging/logtable.py
entsopy/components/marketagreement.py
entsopy/components/marketproduct.py
entsopy/components/panels/fail.py
entsopy/components/panels/success.py
entsopy/components/psrtype.py
entsopy/components/registeredresource.py
entsopy/components/securitytoken.py
entsopy/components/table.py
entsopy/components/ui.py
entsopy/components/welcome.py
entsopy/data/__init__.py
entsopy/data/areas/biddingZone.json
entsopy/data/areas/borderBiddingZone.json
entsopy/data/areas/borderMarketBalancingArea.json
entsopy/data/areas/controlArea.json
entsopy/data/articles/balancing.articles.json
entsopy/data/articles/generation.articles.json
entsopy/data/articles/load.articles.json
entsopy/data/articles/ncm.articles.json
entsopy/data/articles/outages.articles.json
entsopy/data/articles/transmission.articles.json
entsopy/data/types/attributes.json
entsopy/data/types/auctions_type.json
entsopy/data/types/auctions_type_category.json
entsopy/data/types/directions.json
entsopy/data/types/docstatus.json
entsopy/data/types/domains-complete.json
entsopy/data/types/domains.json
entsopy/data/types/market_agreement_contract.json
entsopy/data/types/market_agreement_type.json
entsopy/data/types/market_product.json
entsopy/data/types/psrtypes.json
entsopy/logger/__init__.py
entsopy/logger/logger.py
entsopy/main.py
entsopy/utils/__init__.py
entsopy/utils/const.py
entsopy/utils/csv.py
entsopy/utils/date.py
entsopy/utils/utils.py
pyproject.toml
entsopy-0.2.2.dist-info/METADATA
entsopy-0.2.2.dist-info/WHEEL
entsopy-0.2.2.dist-info/entry_points.txt
entsopy-0.2.2.dist-info/RECORD
